setup.py
longtroll/__init__.py
longtroll/longtroll.py
longtroll.egg-info/PKG-INFO
longtroll.egg-info/SOURCES.txt
longtroll.egg-info/dependency_links.txt
longtroll.egg-info/requires.txt
longtroll.egg-info/top_level.txt