Metadata-Version: 1.0
Name: longtroll
Version: 1.0
Summary: UNKNOWN
Home-page: https://github.com/haldean/longtroll
Author: Will Haldean Brown
Author-email: will.h.brown@gmail.com
License: MIT License
Platform: UNKNOWN
